uecho/__init__.py
uecho/const.py
uecho/controller.py
uecho/device.py
uecho/esv.py
uecho/local_node.py
uecho/manufacturer.py
uecho/message.py
uecho/messages.py
uecho/node.py
uecho/node_profile.py
uecho/object.py
uecho/option.py
uecho/profile.py
uecho/property.py
uecho/remote_node.py
uecho/super_object.py
uecho/frame/__init__.py
uecho/frame/interface.py
uecho/frame/manager.py
uecho/frame/multicast_server.py
uecho/frame/server.py
uecho/frame/unicast_server.py
uecho/log/__init__.py
uecho/log/constants.py
uecho/log/logger.py
uecho/protocol/__init__.py
uecho/protocol/esv.py
uecho/protocol/message.py
uecho/protocol/observer.py
uecho/protocol/property.py
uecho/protocol/subject.py
uecho/std/__init__.py
uecho/std/database.py
uecho/std/manufacturers.py
uecho/std/object.py
uecho/std/objects.py
uecho/std/objects_mra.py
uecho/std/objects_scsl.py
uecho/std/reader.py
uecho/util/__init__.py
uecho/util/bytes.py
uecho/util/hex.py
uecho-1.0.3.dist-info/COPYING
uecho-1.0.3.dist-info/METADATA
uecho-1.0.3.dist-info/WHEEL
uecho-1.0.3.dist-info/top_level.txt
uecho-1.0.3.dist-info/RECORD
