Metadata-Version: 2.1
Name: uecho
Version: 1.0.3
Summary: uEcho for Python is a portable development framework for ECHONET Lite developers.
Home-page: https://github.com/cybergarage/uecho-py.git
Author: Satoshi Konno
Author-email: skonno@cybergarage.org
Classifier: Development Status :: 4 - Beta
Classifier: Environment :: Other Environment
Classifier: Intended Audience :: Developers
Classifier: Operating System :: OS Independent
Classifier: Programming Language :: Python
Classifier: Programming Language :: Python :: 3.6
Classifier: Programming Language :: Python :: 3.7
Classifier: Programming Language :: Python :: 3.8
Classifier: Programming Language :: Python :: 3.9
Classifier: Programming Language :: Python :: 3.10
Classifier: Topic :: System :: Networking
Classifier: License :: OSI Approved :: Apache Software License
License-File: COPYING
Requires-Dist: netifaces
Requires-Dist: typing-extensions
